robo_app/__init__.py
robo_app/application.py
robo_app/constants.py
robo_app/controller.py
robo_app/models.py
robo_app/network.py
robo_app/robot_util.py
robo_app/util.py
robo_app/views.py
robo_app/widgets.py
robotframework_executor-0.1.5.dist-info/LICENSE
robotframework_executor-0.1.5.dist-info/METADATA
robotframework_executor-0.1.5.dist-info/WHEEL
robotframework_executor-0.1.5.dist-info/entry_points.txt
robotframework_executor-0.1.5.dist-info/top_level.txt
robotframework_executor-0.1.5.dist-info/RECORD
