Metadata-Version: 2.1
Name: robotframework-executor
Version: 0.1.5
Summary: A GUI based Robot Test Executor
Home-page: https://github.com/MandyYdnam/Robo_App
Author: Mandeep Dhiman
Author-email: mandeepsinghdhiman@outlook.com
License: UNKNOWN
Platform: UNKNOWN
Classifier: Programming Language :: Python :: 3
Classifier: License :: OSI Approved :: MIT License
Classifier: Operating System :: OS Independent
Requires-Python: >=3.7
Requires-Dist: requests (>=2.22.0)
Requires-Dist: robotframework (>=4.1)
Requires-Dist: matplotlib (>=3.2.1)
